datasette_demo_for_llm_accountant/__init__.py
datasette_demo_for_llm_accountant/templates/llm_accountant.html
datasette_demo_for_llm_accountant-0.1a0.dist-info/licenses/LICENSE
datasette_demo_for_llm_accountant-0.1a0.dist-info/METADATA
datasette_demo_for_llm_accountant-0.1a0.dist-info/WHEEL
datasette_demo_for_llm_accountant-0.1a0.dist-info/entry_points.txt
datasette_demo_for_llm_accountant-0.1a0.dist-info/top_level.txt
datasette_demo_for_llm_accountant-0.1a0.dist-info/RECORD
