Metadata-Version: 2.4
Name: datasette-demo-for-llm-accountant
Version: 0.1a0
Summary: Demo app for LLM accountant
Author: Simon Willison
License-Expression: Apache-2.0
Project-URL: Homepage, https://github.com/datasette/datasette-demo-for-llm-accountant
Project-URL: Changelog, https://github.com/datasette/datasette-demo-for-llm-accountant/releases
Project-URL: Issues, https://github.com/datasette/datasette-demo-for-llm-accountant/issues
Project-URL: CI, https://github.com/datasette/datasette-demo-for-llm-accountant/actions
Classifier: Framework :: Datasette
Requires-Python: >=3.10
License-File: LICENSE
Requires-Dist: datasette>=1.0a21
Requires-Dist: llm
Requires-Dist: datasette-llm-accountant>=0.1a0
Provides-Extra: test
Requires-Dist: pytest; extra == "test"
Requires-Dist: pytest-asyncio; extra == "test"
Dynamic: license-file
